{"cameraMode":{"drawMode":0,"name":"Shaded","section":"Shading Mode"},"sceneLighting":true,"audioPlay":false,"sceneViewState":{"m_AlwaysRefresh":false,"showFog":true,"showSkybox":true,"showFlares":true,"showImageEffects":true,"showParticleSystems":true,"showVisualEffectGraphs":true,"m_FxEnabled":true},"in2DMode":false,"pivot":{"x":236.706787109375,"y":-285.3009948730469,"z":243.29074096679688},"rotation":{"x":0.5004187226295471,"y":0.4542207717895508,"z":-0.35056179761886599,"w":0.6483681797981262},"size":182.16851806640626,"orthographic":false}