{"cameraMode":{"drawMode":0,"name":"Shaded","section":"Shading Mode"},"sceneLighting":true,"audioPlay":false,"sceneViewState":{"m_AlwaysRefresh":false,"showFog":true,"showSkybox":true,"showFlares":true,"showImageEffects":true,"showParticleSystems":true,"showVisualEffectGraphs":true,"m_FxEnabled":true},"in2DMode":false,"pivot":{"x":1.7604248523712159,"y":201.38677978515626,"z":0.9064903259277344},"rotation":{"x":0.15476958453655244,"y":0.06278388947248459,"z":-0.009853100404143334,"w":0.9859117269515991},"size":6.195339679718018,"orthographic":false}